eve_neo4j/__init__.py
eve_neo4j/neo4j.py
eve_neo4j/structures.py
eve_neo4j/utils.py
eve_neo4j/validation.py
eve_neo4j-0.1.4.dist-info/DESCRIPTION.rst
eve_neo4j-0.1.4.dist-info/METADATA
eve_neo4j-0.1.4.dist-info/RECORD
eve_neo4j-0.1.4.dist-info/WHEEL
eve_neo4j-0.1.4.dist-info/dependency_links.txt
eve_neo4j-0.1.4.dist-info/metadata.json
eve_neo4j-0.1.4.dist-info/top_level.txt
