Metadata-Version: 2.0
Name: eve-neo4j
Version: 0.1.4
Summary: Eve Neo4j extension.
Home-page: https://github.com/Abraxas-Biosystems/eve-neo4j
Author: Rodrigo Rodriguez
Author-email: rrodriguez@grupoabraxas.com
License: MIT license
Keywords: eve_neo4j
Platform: UNKNOWN
Classifier: Development Status :: 2 - Pre-Alpha
Classifier: Intended Audience :: Developers
Classifier: License :: OSI Approved :: MIT License
Classifier: Natural Language :: English
Classifier: Programming Language :: Python :: 2
Classifier: Programming Language :: Python :: 2.7
Classifier: Programming Language :: Python :: 3
Classifier: Programming Language :: Python :: 3.3
Classifier: Programming Language :: Python :: 3.4
Classifier: Programming Language :: Python :: 3.5
Requires-Dist: Eve
Requires-Dist: flask-neo4j
Requires-Dist: py2neo
